constants.py
functions.py
nsdpy.py
nsdpy-1.0.0.dist-info/LICENSE
nsdpy-1.0.0.dist-info/METADATA
nsdpy-1.0.0.dist-info/WHEEL
nsdpy-1.0.0.dist-info/entry_points.txt
nsdpy-1.0.0.dist-info/RECORD
