Metadata-Version: 2.1
Name: nsdpy
Version: 1.0.0
Summary: Automatize the download of DNA sequences from NCBI, sort them according to their taxonomy and filter them with a gene name (provided as a regular expression)
Home-page: https://github.com/RaphaelHebert/nsdpy
License: MIT
Keywords: NCBI,Taxonomy,DNA
Author: RaphaelHebert
Author-email: raphaelhebert18@gmail.com
Requires-Python: >=3.8,<4.0
Classifier: License :: OSI Approved :: MIT License
Classifier: Programming Language :: Python :: 3
Classifier: Programming Language :: Python :: 3.8
Classifier: Programming Language :: Python :: 3.9
Classifier: Programming Language :: Python :: 3.10
Classifier: Programming Language :: Python :: 3.11
Requires-Dist: certifi (>=2020.12.5,<2021.0.0)
Requires-Dist: chardet (>=4.0.0,<5.0.0)
Requires-Dist: idna (>=2.10,<3.0)
Requires-Dist: requests (>=2.25.1,<3.0.0)
Requires-Dist: urllib3 (>=1.26.2,<2.0.0)
Project-URL: Repository, https://github.com/RaphaelHebert/nsdpy
